ts2/__init__.py
ts2/ts2.py
ts2-2021.8.2.dist-info/LICENCE
ts2-2021.8.2.dist-info/METADATA
ts2-2021.8.2.dist-info/WHEEL
ts2-2021.8.2.dist-info/top_level.txt
ts2-2021.8.2.dist-info/RECORD
