Metadata-Version: 2.1
Name: ts2
Version: 2021.8.2
Summary: Package used to manage time series with metadata.
Home-page: UNKNOWN
Author: Riccardo Remo Appino
Author-email: riccardoremo.appino@terna.it
License: UNKNOWN
Project-URL: Bug Tracker, https://github.com/pypa/sampleproject/issues
Platform: UNKNOWN
Classifier: Programming Language :: Python :: 3
Requires-Python: >=3.6
License-File: LICENCE
